<?xml version="1.0" encoding="iso-8859-1"?>
<menu layout='1'>
	<side-menu>
		<group title='Links'>
			<item href='http://www.performance.gov.it' target='_blank'>
				Sito di riferimento
			</item>
			<item href='About.do'>
				About
			</item>
		</group>
	</side-menu>
	<main-menu layout='1' groups='6'>
		<group title='Gestione utenti'>
			<item href='GetCreateUser.do'>
				Crea nuovo utente
			</item>
			<item href='ManageUser.do'>
				Gestisci utenti
			</item>
			<item href='ManageExpert.do'>
				Gestisci esperti
			</item>
			<item href='ManageValidator.do'>
				Gestisci validatori
			</item>
		</group>
		<group title='Gestione categorie'>
			<item href='GetCreateCategory.do'>
				Crea nuova categoria
			</item>
			<item href='ManageCategory.do'>
				Gestisci categorie
			</item>
		</group>
		<group title='Gestione strutture'>
			<item href='CreateStrutture.do'>
				Crea nuova struttura
			</item>
			<item href='ManageStrutture.do'>
				Gestisci strutture
			</item>
		</group>
		<group title='Gestione del profilo personale'>
			<item href='GetUpdateUserInfo.do'>
				Modifica informazioni personali
			</item>
			<item href='GetChangePassword.do'>
				Modifica password
			</item>
		</group>
		<group title='Statistiche'>
			<item href='StatisticheDistribuzionePerStato.do'>
				Distribuzione delle segnalazioni per stato
			</item>
			<item href='StatisticheDistribuzionePerCategoria.do'>
				Distribuzione delle segnalazioni per categoria
			</item>
			<item href='StatisticheTempiRisposta.do'>
				Statistiche tempi di risposta
			</item>
		</group>
		<group title='Funzioni di gestione del sistema'>
			<item href='Setup.do'>
				Setup di sistema
			</item>
		</group>
	</main-menu>
</menu>